{
  "BatalhaId": "2026-05-11_03-58-12",
  "Resultado": "Derrota",
  "AcoesIA": {
    "Ataque": 16,
    "Defesa": 29,
    "Esquiva": 11,
    "ContraAtaque": 14,
    "Movimento": 6
  },
  "AcoesJogador": {
    "Ataque": 17,
    "Defesa": 17,
    "Esquiva": 17,
    "ContraAtaque": 16,
    "Movimento": 9
  },
  "Previsao": {
    "Total": 76,
    "Acertos": 17
  },
  "Dano": {
    "CausadoIA": 95,
    "RecebidoIA": 75,
    "CausadoJogador": 75,
    "RecebidoJogador": 95
  },
  "Metricas": {
    "PrecisaoPrevisao": 0.2236842105263158
  }
}