{
  "BatalhaId": "2026-05-11_00-18-15",
  "Resultado": "Vit\u00F3ria",
  "AcoesIA": {
    "Ataque": 12,
    "Defesa": 15,
    "Esquiva": 7,
    "ContraAtaque": 19,
    "Movimento": 4
  },
  "AcoesJogador": {
    "Ataque": 16,
    "Defesa": 12,
    "Esquiva": 11,
    "ContraAtaque": 8,
    "Movimento": 10
  },
  "Previsao": {
    "Total": 57,
    "Acertos": 16
  },
  "Dano": {
    "CausadoIA": 100,
    "RecebidoIA": 70,
    "CausadoJogador": 70,
    "RecebidoJogador": 100
  },
  "Metricas": {
    "PrecisaoPrevisao": 0.2807017543859649
  }
}