{
  "BatalhaId": "2026-05-11_04-32-53",
  "Resultado": "Vit\u00F3ria",
  "AcoesIA": {
    "Ataque": 12,
    "Defesa": 38,
    "Esquiva": 10,
    "ContraAtaque": 27,
    "Movimento": 3
  },
  "AcoesJogador": {
    "Ataque": 16,
    "Defesa": 26,
    "Esquiva": 17,
    "ContraAtaque": 14,
    "Movimento": 17
  },
  "Previsao": {
    "Total": 90,
    "Acertos": 16
  },
  "Dano": {
    "CausadoIA": 100,
    "RecebidoIA": 46,
    "CausadoJogador": 46,
    "RecebidoJogador": 100
  },
  "Metricas": {
    "PrecisaoPrevisao": 0.17777777777777778
  }
}