{
  "BatalhaId": "2026-05-11_04-29-17",
  "Resultado": "Vit\u00F3ria",
  "AcoesIA": {
    "Ataque": 12,
    "Defesa": 25,
    "Esquiva": 4,
    "ContraAtaque": 16,
    "Movimento": 2
  },
  "AcoesJogador": {
    "Ataque": 18,
    "Defesa": 11,
    "Esquiva": 12,
    "ContraAtaque": 13,
    "Movimento": 5
  },
  "Previsao": {
    "Total": 59,
    "Acertos": 18
  },
  "Dano": {
    "CausadoIA": 100,
    "RecebidoIA": 46,
    "CausadoJogador": 46,
    "RecebidoJogador": 100
  },
  "Metricas": {
    "PrecisaoPrevisao": 0.3050847457627119
  }
}