{
  "BatalhaId": "2026-05-10_20-06-49",
  "Resultado": "Vit\u00F3ria",
  "AcoesIA": {
    "Ataque": 13,
    "Defesa": 10,
    "Esquiva": 5,
    "ContraAtaque": 14,
    "Movimento": 3
  },
  "AcoesJogador": {
    "Ataque": 13,
    "Defesa": 4,
    "Esquiva": 18,
    "ContraAtaque": 7,
    "Movimento": 3
  },
  "Previsao": {
    "Total": 45,
    "Acertos": 12
  },
  "Dano": {
    "CausadoIA": 96,
    "RecebidoIA": 64,
    "CausadoJogador": 64,
    "RecebidoJogador": 96
  },
  "Metricas": {
    "PrecisaoPrevisao": 0.26666666666666666
  }
}