{
  "BatalhaId": "2026-05-10_19-28-56",
  "Resultado": "Vit\u00F3ria",
  "AcoesIA": {
    "Ataque": 12,
    "Defesa": 10,
    "Esquiva": 1,
    "ContraAtaque": 10,
    "Movimento": 0
  },
  "AcoesJogador": {
    "Ataque": 12,
    "Defesa": 4,
    "Esquiva": 12,
    "ContraAtaque": 1,
    "Movimento": 4
  },
  "Previsao": {
    "Total": 33,
    "Acertos": 11
  },
  "Dano": {
    "CausadoIA": 96,
    "RecebidoIA": 59,
    "CausadoJogador": 59,
    "RecebidoJogador": 96
  },
  "Metricas": {
    "PrecisaoPrevisao": 0.3333333333333333
  }
}