{
  "Nome": "2026-05-11_01-02-24",
  "Turnos": [
    {
      "Numero": 1,
      "Jogador": "Soldado Padrao",
      "AcaoJogador": "Ataque",
      "Inimigo": "Inimigo",
      "AcaoInimigo": "Esquiva",
      "VidaJogador": 100,
      "VidaInimigo": 70
    },
    {
      "Numero": 2,
      "Jogador": "Soldado Padrao",
      "AcaoJogador": "ContraAtaque",
      "Inimigo": "Inimigo",
      "AcaoInimigo": "Movimento",
      "VidaJogador": 100,
      "VidaInimigo": 70
    },
    {
      "Numero": 3,
      "Jogador": "Soldado Padrao",
      "AcaoJogador": "Defesa",
      "Inimigo": "Inimigo",
      "AcaoInimigo": "Ataque",
      "VidaJogador": 93,
      "VidaInimigo": 70
    },
    {
      "Numero": 4,
      "Jogador": "Soldado Padrao",
      "AcaoJogador": "Esquiva",
      "Inimigo": "Inimigo",
      "AcaoInimigo": "ContraAtaque",
      "VidaJogador": 93,
      "VidaInimigo": 70
    },
    {
      "Numero": 5,
      "Jogador": "Soldado Padrao",
      "AcaoJogador": "Defesa",
      "Inimigo": "Inimigo",
      "AcaoInimigo": "ContraAtaque",
      "VidaJogador": 93,
      "VidaInimigo": 70
    },
    {
      "Numero": 6,
      "Jogador": "Soldado Padrao",
      "AcaoJogador": "Defesa",
      "Inimigo": "Inimigo",
      "AcaoInimigo": "Ataque",
      "VidaJogador": 90,
      "VidaInimigo": 70
    },
    {
      "Numero": 7,
      "Jogador": "Soldado Padrao",
      "AcaoJogador": "ContraAtaque",
      "Inimigo": "Inimigo",
      "AcaoInimigo": "ContraAtaque",
      "VidaJogador": 90,
      "VidaInimigo": 70
    },
    {
      "Numero": 8,
      "Jogador": "Soldado Padrao",
      "AcaoJogador": "Movimento",
      "Inimigo": "Inimigo",
      "AcaoInimigo": "Ataque",
      "VidaJogador": 82,
      "VidaInimigo": 70
    },
    {
      "Numero": 9,
      "Jogador": "Soldado Padrao",
      "AcaoJogador": "Movimento",
      "Inimigo": "Inimigo",
      "AcaoInimigo": "ContraAtaque",
      "VidaJogador": 82,
      "VidaInimigo": 70
    },
    {
      "Numero": 10,
      "Jogador": "Soldado Padrao",
      "AcaoJogador": "Ataque",
      "Inimigo": "Inimigo",
      "AcaoInimigo": "Defesa",
      "VidaJogador": 82,
      "VidaInimigo": 67
    },
    {
      "Numero": 11,
      "Jogador": "Soldado Padrao",
      "AcaoJogador": "ContraAtaque",
      "Inimigo": "Inimigo",
      "AcaoInimigo": "Defesa",
      "VidaJogador": 82,
      "VidaInimigo": 67
    },
    {
      "Numero": 12,
      "Jogador": "Soldado Padrao",
      "AcaoJogador": "Defesa",
      "Inimigo": "Inimigo",
      "AcaoInimigo": "Movimento",
      "VidaJogador": 82,
      "VidaInimigo": 67
    },
    {
      "Numero": 13,
      "Jogador": "Soldado Padrao",
      "AcaoJogador": "Defesa",
      "Inimigo": "Inimigo",
      "AcaoInimigo": "Ataque",
      "VidaJogador": 75,
      "VidaInimigo": 67
    },
    {
      "Numero": 14,
      "Jogador": "Soldado Padrao",
      "AcaoJogador": "Ataque",
      "Inimigo": "Inimigo",
      "AcaoInimigo": "Esquiva",
      "VidaJogador": 75,
      "VidaInimigo": 67
    },
    {
      "Numero": 15,
      "Jogador": "Soldado Padrao",
      "AcaoJogador": "Defesa",
      "Inimigo": "Inimigo",
      "AcaoInimigo": "Defesa",
      "VidaJogador": 75,
      "VidaInimigo": 67
    },
    {
      "Numero": 16,
      "Jogador": "Soldado Padrao",
      "AcaoJogador": "Defesa",
      "Inimigo": "Inimigo",
      "AcaoInimigo": "Defesa",
      "VidaJogador": 75,
      "VidaInimigo": 67
    },
    {
      "Numero": 17,
      "Jogador": "Soldado Padrao",
      "AcaoJogador": "Esquiva",
      "Inimigo": "Inimigo",
      "AcaoInimigo": "Ataque",
      "VidaJogador": 75,
      "VidaInimigo": 67
    },
    {
      "Numero": 18,
      "Jogador": "Soldado Padrao",
      "AcaoJogador": "Ataque",
      "Inimigo": "Inimigo",
      "AcaoInimigo": "Ataque",
      "VidaJogador": 67,
      "VidaInimigo": 62
    },
    {
      "Numero": 19,
      "Jogador": "Soldado Padrao",
      "AcaoJogador": "Movimento",
      "Inimigo": "Inimigo",
      "AcaoInimigo": "Defesa",
      "VidaJogador": 67,
      "VidaInimigo": 62
    },
    {
      "Numero": 20,
      "Jogador": "Soldado Padrao",
      "AcaoJogador": "Movimento",
      "Inimigo": "Inimigo",
      "AcaoInimigo": "Defesa",
      "VidaJogador": 67,
      "VidaInimigo": 62
    },
    {
      "Numero": 21,
      "Jogador": "Soldado Padrao",
      "AcaoJogador": "Esquiva",
      "Inimigo": "Inimigo",
      "AcaoInimigo": "Defesa",
      "VidaJogador": 67,
      "VidaInimigo": 62
    },
    {
      "Numero": 22,
      "Jogador": "Soldado Padrao",
      "AcaoJogador": "Esquiva",
      "Inimigo": "Inimigo",
      "AcaoInimigo": "ContraAtaque",
      "VidaJogador": 67,
      "VidaInimigo": 62
    },
    {
      "Numero": 23,
      "Jogador": "Soldado Padrao",
      "AcaoJogador": "Defesa",
      "Inimigo": "Inimigo",
      "AcaoInimigo": "Defesa",
      "VidaJogador": 67,
      "VidaInimigo": 62
    },
    {
      "Numero": 24,
      "Jogador": "Soldado Padrao",
      "AcaoJogador": "ContraAtaque",
      "Inimigo": "Inimigo",
      "AcaoInimigo": "Defesa",
      "VidaJogador": 67,
      "VidaInimigo": 62
    },
    {
      "Numero": 25,
      "Jogador": "Soldado Padrao",
      "AcaoJogador": "ContraAtaque",
      "Inimigo": "Inimigo",
      "AcaoInimigo": "Defesa",
      "VidaJogador": 67,
      "VidaInimigo": 62
    },
    {
      "Numero": 26,
      "Jogador": "Soldado Padrao",
      "AcaoJogador": "Movimento",
      "Inimigo": "Inimigo",
      "AcaoInimigo": "Defesa",
      "VidaJogador": 67,
      "VidaInimigo": 62
    },
    {
      "Numero": 27,
      "Jogador": "Soldado Padrao",
      "AcaoJogador": "Defesa",
      "Inimigo": "Inimigo",
      "AcaoInimigo": "Esquiva",
      "VidaJogador": 67,
      "VidaInimigo": 62
    },
    {
      "Numero": 28,
      "Jogador": "Soldado Padrao",
      "AcaoJogador": "Ataque",
      "Inimigo": "Inimigo",
      "AcaoInimigo": "Defesa",
      "VidaJogador": 67,
      "VidaInimigo": 62
    },
    {
      "Numero": 29,
      "Jogador": "Soldado Padrao",
      "AcaoJogador": "ContraAtaque",
      "Inimigo": "Inimigo",
      "AcaoInimigo": "Defesa",
      "VidaJogador": 67,
      "VidaInimigo": 62
    },
    {
      "Numero": 30,
      "Jogador": "Soldado Padrao",
      "AcaoJogador": "Esquiva",
      "Inimigo": "Inimigo",
      "AcaoInimigo": "ContraAtaque",
      "VidaJogador": 67,
      "VidaInimigo": 62
    },
    {
      "Numero": 31,
      "Jogador": "Soldado Padrao",
      "AcaoJogador": "Defesa",
      "Inimigo": "Inimigo",
      "AcaoInimigo": "ContraAtaque",
      "VidaJogador": 67,
      "VidaInimigo": 62
    },
    {
      "Numero": 32,
      "Jogador": "Soldado Padrao",
      "AcaoJogador": "ContraAtaque",
      "Inimigo": "Inimigo",
      "AcaoInimigo": "Ataque",
      "VidaJogador": 63,
      "VidaInimigo": 57
    },
    {
      "Numero": 33,
      "Jogador": "Soldado Padrao",
      "AcaoJogador": "Esquiva",
      "Inimigo": "Inimigo",
      "AcaoInimigo": "ContraAtaque",
      "VidaJogador": 63,
      "VidaInimigo": 57
    },
    {
      "Numero": 34,
      "Jogador": "Soldado Padrao",
      "AcaoJogador": "Esquiva",
      "Inimigo": "Inimigo",
      "AcaoInimigo": "Defesa",
      "VidaJogador": 63,
      "VidaInimigo": 57
    },
    {
      "Numero": 35,
      "Jogador": "Soldado Padrao",
      "AcaoJogador": "ContraAtaque",
      "Inimigo": "Inimigo",
      "AcaoInimigo": "ContraAtaque",
      "VidaJogador": 63,
      "VidaInimigo": 57
    },
    {
      "Numero": 36,
      "Jogador": "Soldado Padrao",
      "AcaoJogador": "Movimento",
      "Inimigo": "Inimigo",
      "AcaoInimigo": "ContraAtaque",
      "VidaJogador": 63,
      "VidaInimigo": 57
    },
    {
      "Numero": 37,
      "Jogador": "Soldado Padrao",
      "AcaoJogador": "Esquiva",
      "Inimigo": "Inimigo",
      "AcaoInimigo": "ContraAtaque",
      "VidaJogador": 63,
      "VidaInimigo": 57
    },
    {
      "Numero": 38,
      "Jogador": "Soldado Padrao",
      "AcaoJogador": "Defesa",
      "Inimigo": "Inimigo",
      "AcaoInimigo": "Defesa",
      "VidaJogador": 63,
      "VidaInimigo": 57
    },
    {
      "Numero": 39,
      "Jogador": "Soldado Padrao",
      "AcaoJogador": "Defesa",
      "Inimigo": "Inimigo",
      "AcaoInimigo": "Movimento",
      "VidaJogador": 63,
      "VidaInimigo": 57
    },
    {
      "Numero": 40,
      "Jogador": "Soldado Padrao",
      "AcaoJogador": "Ataque",
      "Inimigo": "Inimigo",
      "AcaoInimigo": "Ataque",
      "VidaJogador": 51,
      "VidaInimigo": 52
    },
    {
      "Numero": 41,
      "Jogador": "Soldado Padrao",
      "AcaoJogador": "ContraAtaque",
      "Inimigo": "Inimigo",
      "AcaoInimigo": "Esquiva",
      "VidaJogador": 51,
      "VidaInimigo": 52
    },
    {
      "Numero": 42,
      "Jogador": "Soldado Padrao",
      "AcaoJogador": "Ataque",
      "Inimigo": "Inimigo",
      "AcaoInimigo": "ContraAtaque",
      "VidaJogador": 47,
      "VidaInimigo": 49
    },
    {
      "Numero": 43,
      "Jogador": "Soldado Padrao",
      "AcaoJogador": "Defesa",
      "Inimigo": "Inimigo",
      "AcaoInimigo": "Defesa",
      "VidaJogador": 47,
      "VidaInimigo": 49
    },
    {
      "Numero": 44,
      "Jogador": "Soldado Padrao",
      "AcaoJogador": "Defesa",
      "Inimigo": "Inimigo",
      "AcaoInimigo": "ContraAtaque",
      "VidaJogador": 47,
      "VidaInimigo": 49
    },
    {
      "Numero": 45,
      "Jogador": "Soldado Padrao",
      "AcaoJogador": "Defesa",
      "Inimigo": "Inimigo",
      "AcaoInimigo": "Defesa",
      "VidaJogador": 47,
      "VidaInimigo": 49
    },
    {
      "Numero": 46,
      "Jogador": "Soldado Padrao",
      "AcaoJogador": "Ataque",
      "Inimigo": "Inimigo",
      "AcaoInimigo": "Movimento",
      "VidaJogador": 47,
      "VidaInimigo": 44
    },
    {
      "Numero": 47,
      "Jogador": "Soldado Padrao",
      "AcaoJogador": "Defesa",
      "Inimigo": "Inimigo",
      "AcaoInimigo": "Ataque",
      "VidaJogador": 40,
      "VidaInimigo": 44
    },
    {
      "Numero": 48,
      "Jogador": "Soldado Padrao",
      "AcaoJogador": "Ataque",
      "Inimigo": "Inimigo",
      "AcaoInimigo": "Esquiva",
      "VidaJogador": 40,
      "VidaInimigo": 39
    },
    {
      "Numero": 49,
      "Jogador": "Soldado Padrao",
      "AcaoJogador": "Movimento",
      "Inimigo": "Inimigo",
      "AcaoInimigo": "Ataque",
      "VidaJogador": 32,
      "VidaInimigo": 39
    },
    {
      "Numero": 50,
      "Jogador": "Soldado Padrao",
      "AcaoJogador": "Defesa",
      "Inimigo": "Inimigo",
      "AcaoInimigo": "Ataque",
      "VidaJogador": 29,
      "VidaInimigo": 39
    },
    {
      "Numero": 51,
      "Jogador": "Soldado Padrao",
      "AcaoJogador": "ContraAtaque",
      "Inimigo": "Inimigo",
      "AcaoInimigo": "Movimento",
      "VidaJogador": 29,
      "VidaInimigo": 39
    },
    {
      "Numero": 52,
      "Jogador": "Soldado Padrao",
      "AcaoJogador": "Ataque",
      "Inimigo": "Inimigo",
      "AcaoInimigo": "Ataque",
      "VidaJogador": 17,
      "VidaInimigo": 34
    },
    {
      "Numero": 53,
      "Jogador": "Soldado Padrao",
      "AcaoJogador": "Esquiva",
      "Inimigo": "Inimigo",
      "AcaoInimigo": "Ataque",
      "VidaJogador": 17,
      "VidaInimigo": 34
    },
    {
      "Numero": 54,
      "Jogador": "Soldado Padrao",
      "AcaoJogador": "Esquiva",
      "Inimigo": "Inimigo",
      "AcaoInimigo": "Ataque",
      "VidaJogador": 9,
      "VidaInimigo": 34
    },
    {
      "Numero": 55,
      "Jogador": "Soldado Padrao",
      "AcaoJogador": "Movimento",
      "Inimigo": "Inimigo",
      "AcaoInimigo": "Defesa",
      "VidaJogador": 9,
      "VidaInimigo": 34
    },
    {
      "Numero": 56,
      "Jogador": "Soldado Padrao",
      "AcaoJogador": "ContraAtaque",
      "Inimigo": "Inimigo",
      "AcaoInimigo": "Defesa",
      "VidaJogador": 9,
      "VidaInimigo": 34
    },
    {
      "Numero": 57,
      "Jogador": "Soldado Padrao",
      "AcaoJogador": "Ataque",
      "Inimigo": "Inimigo",
      "AcaoInimigo": "Esquiva",
      "VidaJogador": 9,
      "VidaInimigo": 29
    },
    {
      "Numero": 58,
      "Jogador": "Soldado Padrao",
      "AcaoJogador": "Esquiva",
      "Inimigo": "Inimigo",
      "AcaoInimigo": "Ataque",
      "VidaJogador": 9,
      "VidaInimigo": 29
    },
    {
      "Numero": 59,
      "Jogador": "Soldado Padrao",
      "AcaoJogador": "ContraAtaque",
      "Inimigo": "Inimigo",
      "AcaoInimigo": "ContraAtaque",
      "VidaJogador": 9,
      "VidaInimigo": 29
    },
    {
      "Numero": 60,
      "Jogador": "Soldado Padrao",
      "AcaoJogador": "Esquiva",
      "Inimigo": "Inimigo",
      "AcaoInimigo": "Ataque",
      "VidaJogador": 1,
      "VidaInimigo": 29
    },
    {
      "Numero": 61,
      "Jogador": "Soldado Padrao",
      "AcaoJogador": "Esquiva",
      "Inimigo": "Inimigo",
      "AcaoInimigo": "ContraAtaque",
      "VidaJogador": 1,
      "VidaInimigo": 29
    },
    {
      "Numero": 62,
      "Jogador": "Soldado Padrao",
      "AcaoJogador": "Movimento",
      "Inimigo": "Inimigo",
      "AcaoInimigo": "Defesa",
      "VidaJogador": 1,
      "VidaInimigo": 29
    },
    {
      "Numero": 63,
      "Jogador": "Soldado Padrao",
      "AcaoJogador": "ContraAtaque",
      "Inimigo": "Inimigo",
      "AcaoInimigo": "Esquiva",
      "VidaJogador": 1,
      "VidaInimigo": 29
    },
    {
      "Numero": 64,
      "Jogador": "Soldado Padrao",
      "AcaoJogador": "Movimento",
      "Inimigo": "Inimigo",
      "AcaoInimigo": "ContraAtaque",
      "VidaJogador": 1,
      "VidaInimigo": 29
    },
    {
      "Numero": 65,
      "Jogador": "Soldado Padrao",
      "AcaoJogador": "ContraAtaque",
      "Inimigo": "Inimigo",
      "AcaoInimigo": "Movimento",
      "VidaJogador": 1,
      "VidaInimigo": 29
    },
    {
      "Numero": 66,
      "Jogador": "Soldado Padrao",
      "AcaoJogador": "Defesa",
      "Inimigo": "Inimigo",
      "AcaoInimigo": "Ataque",
      "VidaJogador": 0,
      "VidaInimigo": 29
    }
  ]
}