{
  "BatalhaId": "2026-05-10_17-06-44",
  "Resultado": "Derrota",
  "AcoesIA": {
    "Ataque": 9,
    "Defesa": 4,
    "Esquiva": 5,
    "ContraAtaque": 3,
    "Movimento": 0
  },
  "AcoesJogador": {
    "Ataque": 7,
    "Defesa": 5,
    "Esquiva": 0,
    "ContraAtaque": 5,
    "Movimento": 4
  },
  "Previsao": {
    "Total": 21,
    "Acertos": 7
  },
  "Dano": {
    "CausadoIA": 56,
    "RecebidoIA": 75,
    "CausadoJogador": 75,
    "RecebidoJogador": 56
  },
  "Metricas": {
    "PrecisaoPrevisao": 0.3333333333333333
  }
}