{
  "BatalhaId": "2026-05-10_16-47-58",
  "Resultado": "Derrota",
  "AcoesIA": {
    "Ataque": 10,
    "Defesa": 4,
    "Esquiva": 4,
    "ContraAtaque": 2,
    "Movimento": 1
  },
  "AcoesJogador": {
    "Ataque": 8,
    "Defesa": 1,
    "Esquiva": 2,
    "ContraAtaque": 4,
    "Movimento": 6
  },
  "Previsao": {
    "Total": 21,
    "Acertos": 5
  },
  "Dano": {
    "CausadoIA": 76,
    "RecebidoIA": 75,
    "CausadoJogador": 75,
    "RecebidoJogador": 76
  },
  "Metricas": {
    "PrecisaoPrevisao": 0.23809523809523808
  }
}